cybermoon/__init__.py
cybermoon/basic_functions.py
cybermoon/enemy.py
cybermoon/grenade.py
cybermoon/high_score_list.py
cybermoon/main.py
cybermoon/menu_shrap.py
cybermoon/play.py
cybermoon/player.py
cybermoon/player_enemy_control.py
cybermoon/shrap.py
cybermoon/sound_effects.py
cybermoon/the_main_menu.py
cybermoon/sounds/allobtain.wav
cybermoon/sounds/nextlevel.wav
cybermoon/sounds/obtain1.wav
cybermoon/sounds/obtain2.wav
cybermoon-1.0.0.dist-info/licenses/LICENSE
cybermoon-1.0.0.dist-info/METADATA
cybermoon-1.0.0.dist-info/WHEEL
cybermoon-1.0.0.dist-info/top_level.txt
cybermoon-1.0.0.dist-info/RECORD
