Metadata-Version: 2.4
Name: cybermoon
Version: 1.0.0
Summary: A futuristic pygame
Author-email: Anders Reenberg Andersen <andersra@live.dk>
Project-URL: Homepage, https://github.com/areenberg/CyberMoon
Project-URL: Issues, https://github.com/areenberg/CyberMoon/issues
Classifier: Development Status :: 5 - Production/Stable
Classifier: Programming Language :: Python :: 3
Classifier: License :: OSI Approved :: MIT License
Classifier: Operating System :: OS Independent
Requires-Python: >=3.10
License-File: LICENSE
Requires-Dist: pygame>=2.3.0
Requires-Dist: pyautogui>=0.9.53
Dynamic: license-file
